fotmob_api/__init__.py
fotmob_api/fotmob_api.py
fotmob_api-1.0.0.dist-info/METADATA
fotmob_api-1.0.0.dist-info/WHEEL
fotmob_api-1.0.0.dist-info/top_level.txt
fotmob_api-1.0.0.dist-info/RECORD
