Metadata-Version: 2.1
Name: fotmob-api
Version: 1.0.0
Summary: API wrapper for Fotmob
Author: Christian Rønsholt
Author-email: ronsholt32@gmail.com
License: MIT
Requires-Python: >=3.7
Provides-Extra: test
Provides-Extra: examples
